veinmind_common/__init__.py
veinmind_common/service/__init__.py
veinmind_common/service/report.py
veinmind_common-1.2.0.dist-info/LICENSE
veinmind_common-1.2.0.dist-info/METADATA
veinmind_common-1.2.0.dist-info/WHEEL
veinmind_common-1.2.0.dist-info/top_level.txt
veinmind_common-1.2.0.dist-info/RECORD
