Metadata-Version: 2.1
Name: veinmind-common
Version: 1.2.0
Summary: veinmind_common with python
Home-page: https://github.com/chaitin/veinmind-common-python
Author: chaitin
Author-email: info@chaitin.com
License: MIT
Platform: UNKNOWN
Classifier: License :: OSI Approved :: MIT License
Classifier: Programming Language :: Python
Classifier: Programming Language :: Python :: 3
Classifier: Programming Language :: Python :: 3.6
Classifier: Programming Language :: Python :: Implementation :: CPython
Classifier: Programming Language :: Python :: Implementation :: PyPy
Requires-Python: >=3.6.0
License-File: LICENSE
Requires-Dist: jsonpickle
Requires-Dist: veinmind
Requires-Dist: dataclasses
